{"options":{},"indexes":[{"v":{"$numberInt":"2"},"key":{"_id":{"$numberInt":"1"}},"name":"_id_","ns":"mmcmrtadb.kmls"},{"v":{"$numberInt":"2"},"unique":true,"key":{"line_en":{"$numberInt":"1"}},"name":"line_en_1","ns":"mmcmrtadb.kmls","background":true},{"v":{"$numberInt":"2"},"unique":true,"key":{"line_th":{"$numberInt":"1"}},"name":"line_th_1","background":true,"ns":"mmcmrtadb.kmls"},{"v":{"$numberInt":"2"},"unique":true,"key":{"url":{"$numberInt":"1"}},"name":"url_1","background":true,"ns":"mmcmrtadb.kmls"}],"uuid":"e1f724d4ab914d12870644f9b52656a6"}